Metadata-Version: 2.4
Name: adafruit-circuitpython-hue
Version: 2.0.4
Summary: CircuitPython helper library for the Philips Hue
Author-email: Adafruit Industries <circuitpython@adafruit.com>
License: MIT
Project-URL: Homepage, https://github.com/adafruit/Adafruit_CircuitPython_Hue
Keywords: adafruit,blinka,circuitpython,micropython,hue,philips,bulb,light,bridge
Classifier: Intended Audience :: Developers
Classifier: Topic :: Software Development :: Libraries
Classifier: Topic :: Software Development :: Embedded Systems
Classifier: Topic :: System :: Hardware
Classifier: License :: OSI Approved :: MIT License
Classifier: Programming Language :: Python :: 3
License-File: LICENSE
Requires-Dist: Adafruit-Blinka
Requires-Dist: adafruit-circuitpython-simpleio
Requires-Dist: adafruit-circuitpython-esp32spi
Requires-Dist: adafruit-circuitpython-typing
Provides-Extra: optional
Dynamic: license-file
